snakifyer/__init__.py
snakifyer/api.py
snakifyer/cli.py
snakifyer/core.py
snakifyer-2.0.0.dist-info/LICENSE
snakifyer-2.0.0.dist-info/METADATA
snakifyer-2.0.0.dist-info/WHEEL
snakifyer-2.0.0.dist-info/entry_points.txt
snakifyer-2.0.0.dist-info/top_level.txt
snakifyer-2.0.0.dist-info/RECORD
