Metadata-Version: 2.1
Name: snakifyer
Version: 2.0.0
Summary: A simple to bot to automate problem submissions on snakify.org 
Home-page: https://github.com/akashrchandran/snakifyer
Author: Akash R Chandran
Author-email: chandranrakash@gmail.com
Classifier: Programming Language :: Python :: 3
Classifier: License :: OSI Approved :: MIT License
Classifier: Operating System :: OS Independent
Requires-Python: >=3.6
License-File: LICENSE
Requires-Dist: beautifulsoup4
Requires-Dist: requests
Requires-Dist: rich
